humps/__init__.py
humps/camel.py
humps-0.2.2.dist-info/DESCRIPTION.rst
humps-0.2.2.dist-info/METADATA
humps-0.2.2.dist-info/RECORD
humps-0.2.2.dist-info/WHEEL
humps-0.2.2.dist-info/metadata.json
humps-0.2.2.dist-info/top_level.txt
tests/__init__.py
tests/test_humps.py
